{
  "industrial_pseudo": [
    "syngas",
    "vegetable_oil",
    "biodiesel",
    "glycerin",
    "naphtha",
    "kerosene",
    "diesel",
    "atmospheric_residue",
    "crude_oil"
  ],
  "food_pseudo_allowed": [
    "sucrose",
    "glucose"
  ],
  "notes": {
    "industrial_pseudo": "Pseudo-componentes industriales que el Frente C reemplazará por moléculas reales. Auditor genera warning.",
    "food_pseudo_allowed": "Pseudo-componentes de industria alimentaria que se mantienen como aproximaciones documentadas. Auditor genera INFO (no warning)."
  }
}
